README.md
setup.py
deep_tabular_augmentation/__init__.py
deep_tabular_augmentation/callbacks.py
deep_tabular_augmentation/common.py
deep_tabular_augmentation/dataloaders.py
deep_tabular_augmentation/model_part.py
deep_tabular_augmentation/runner.py
deep_tabular_augmentation.egg-info/PKG-INFO
deep_tabular_augmentation.egg-info/SOURCES.txt
deep_tabular_augmentation.egg-info/dependency_links.txt
deep_tabular_augmentation.egg-info/top_level.txt