Metadata-Version: 2.1
Name: deep-tabular-augmentation
Version: 0.5.2
Summary: Small package for data augmentation via Deep Learning
Home-page: https://github.com/lschmiddey/deep_tabular_augmentation
Author: Lasse Schmidt
Author-email: lasse.schmidt@live.de
License: UNKNOWN
Platform: UNKNOWN
Classifier: Programming Language :: Python :: 3
Classifier: License :: OSI Approved :: MIT License
Classifier: Operating System :: OS Independent
Requires-Python: >=3.6
